{"assets/images/background.png":["assets/images/background.png"],"assets/images/splash.png":["assets/images/splash.png"],"assets/svgs/Path%208764.svg":["assets/svgs/Path%208764.svg"],"assets/svgs/analytical.svg":["assets/svgs/analytical.svg"],"assets/svgs/analyticalreports.svg":["assets/svgs/analyticalreports.svg"],"assets/svgs/attachment.svg":["assets/svgs/attachment.svg"],"assets/svgs/backarrow.svg":["assets/svgs/backarrow.svg"],"assets/svgs/button.svg":["assets/svgs/button.svg"],"assets/svgs/department.svg":["assets/svgs/department.svg"],"assets/svgs/departmentreports.svg":["assets/svgs/departmentreports.svg"],"assets/svgs/dropdown.svg":["assets/svgs/dropdown.svg"],"assets/svgs/history.svg":["assets/svgs/history.svg"],"assets/svgs/home.svg":["assets/svgs/home.svg"],"assets/svgs/illustration.svg":["assets/svgs/illustration.svg"],"assets/svgs/industry.svg":["assets/svgs/industry.svg"],"assets/svgs/industryreports.svg":["assets/svgs/industryreports.svg"],"assets/svgs/logo.svg":["assets/svgs/logo.svg"],"assets/svgs/logout.svg":["assets/svgs/logout.svg"],"assets/svgs/manageprofile.svg":["assets/svgs/manageprofile.svg"],"assets/svgs/notification.svg":["assets/svgs/notification.svg"],"assets/svgs/notificationicon.svg":["assets/svgs/notificationicon.svg"],"assets/svgs/operational.svg":["assets/svgs/operational.svg"],"assets/svgs/operationalreports.svg":["assets/svgs/operationalreports.svg"],"assets/svgs/password.svg":["assets/svgs/password.svg"],"assets/svgs/product.svg":["assets/svgs/product.svg"],"assets/svgs/productreports.svg":["assets/svgs/productreports.svg"],"assets/svgs/professional.svg":["assets/svgs/professional.svg"],"assets/svgs/profile.svg":["assets/svgs/profile.svg"],"assets/svgs/progress.svg":["assets/svgs/progress.svg"],"assets/svgs/progressreports.svg":["assets/svgs/progressreports.svg"],"assets/svgs/promotionalnotification.svg":["assets/svgs/promotionalnotification.svg"],"assets/svgs/reports.svg":["assets/svgs/reports.svg"],"assets/svgs/username.svg":["assets/svgs/username.svg"],"packages/cupertino_icons/assets/CupertinoIcons.ttf":["packages/cupertino_icons/assets/CupertinoIcons.ttf"]}